{
  "window_title":"RomInntrengere v0.1",
  "start_menu":false,
  "fullscreen":false,

  "grid_X": 32,
  "grid_Y": 18,
  "game_resolution_X":1920,
  "game_resolution_Y":1080,

  "OrthographicCamera_deadzone_X":0.5,
  "OrthographicCamera_deadzone_Y":0.5,
  "OrthographicCamera_dampening":0.1,

  "Physics_use_quadtree": true,
  "Physics_use_raycast": true,
  "Physics_use_shadowSweep": true,
  "Physics_circle_line_resolution": 12,
  "Physics_rigidbody2d_VelocityVerlet": true,
  "Physics_rigidbody2d_friction":0.1,
  "Physics_rigidbody2d_velocity_threshhold":10.0,

  "RedRifle_projectile_speed":400,

  "Alien_attack_distance": 500,
  "Alien_flee_distance": 900,

  "Alien_green_speed": 450,
  "Alien_green_max_health": 30,
  "Alien_green_bullet_dmg": 10,
  "Alien_worm_max_health": 50,
  "Alien_worm_hit_dmg": 20,
  "Alien_zombie_max_health": 40,
  "Alien_zombie_hit_dmg": 50,
  "Alien_eye_max_health": 60,
  "Alien_eye_hit_dmg": 2,
  "Alien_glow_max_health": 30,
  "Alien_glow_bullet_dmg": 5,
  "Alien_mother_max_health": 100,
  "Alien_mother_hit_dmg": 1,

  "player_health":100,
  "player_angular_dampening":0.1

}